toon/__init__.py
toon/cli.py
toon/constants.py
toon/decoder.py
toon/encoder.py
toon/pydantic_converter.py
toon/utils.py
toonify-1.4.0.dist-info/METADATA
toonify-1.4.0.dist-info/WHEEL
toonify-1.4.0.dist-info/entry_points.txt
toonify-1.4.0.dist-info/licenses/LICENSE
toonify-1.4.0.dist-info/RECORD
