Metadata-Version: 2.3
Name: toonify
Version: 1.4.0
Summary: TOON (Token-Oriented Object Notation) - A compact, human-readable serialization format for LLMs
Project-URL: Homepage, https://github.com/ScrapeGraphAI/toonify
Project-URL: Repository, https://github.com/ScrapeGraphAI/toonify
Project-URL: Documentation, https://github.com/ScrapeGraphAI/toonify#readme
Author: TOON Format Contributors
License: MIT
Keywords: csv,json,llm,serialization,token-efficient,toon
Classifier: Development Status :: 4 - Beta
Classifier: Intended Audience :: Developers
Classifier: License :: OSI Approved :: MIT License
Classifier: Programming Language :: Python :: 3
Classifier: Programming Language :: Python :: 3.8
Classifier: Programming Language :: Python :: 3.9
Classifier: Programming Language :: Python :: 3.10
Classifier: Programming Language :: Python :: 3.11
Classifier: Programming Language :: Python :: 3.12
Classifier: Topic :: Software Development :: Libraries :: Python Modules
Classifier: Topic :: Text Processing
Requires-Python: >=3.8
Requires-Dist: tiktoken>=0.5.0
Provides-Extra: all
Requires-Dist: pydantic>=1.10.0; extra == 'all'
Provides-Extra: dev
Requires-Dist: pytest-cov>=4.0.0; extra == 'dev'
Requires-Dist: pytest>=7.0.0; extra == 'dev'
Provides-Extra: pydantic
Requires-Dist: pydantic>=1.10.0; extra == 'pydantic'
